CHANGES.txt
README.txt
TODO.txt
bootstrap.py
buildout.cfg
setup.py
src/zope/__init__.py
src/zope.psycopgda.egg-info/PKG-INFO
src/zope.psycopgda.egg-info/SOURCES.txt
src/zope.psycopgda.egg-info/dependency_links.txt
src/zope.psycopgda.egg-info/namespace_packages.txt
src/zope.psycopgda.egg-info/not-zip-safe
src/zope.psycopgda.egg-info/requires.txt
src/zope.psycopgda.egg-info/top_level.txt
src/zope/psycopgda/__init__.py
src/zope/psycopgda/adapter.py
src/zope/psycopgda/configure.zcml
src/zope/psycopgda/tests.py